Workbook
Name Slicer_Category: #N/A
Name Slicer_Category1: #N/A
Name Slicer_Month_: #N/A
Name Slicer_MonthName: #N/A
Name Slicer_Salesperson: #N/A
Name Slicer_Salesperson1: #N/A
Name Slicer_State: #N/A
Name Slicer_State2: #N/A
Name Slicer_Year: #N/A
Name Slicer_Year1: #N/A

Sheet Customers
A1: Customer ID | B1: Customer Name | C1: City | D1: State
A2: C001 | B2: Arun | C2: Chennai | D2: Tamil Nadu
A3: C002 | B3: Priya | C3: Bangalore | D3: Karnataka
A4: C003 | B4: Rahul | C4: Hyderabad | D4: Telangana
A5: C004 | B5: Divya | C5: Chennai | D5: Tamil Nadu
A6: C005 | B6: Kiran | C6: Kochi | D6: Kerala
A7: C006 | B7: Meena | C7: Bangalore | D7: Karnataka
A8: C007 | B8: Vignesh | C8: Madurai | D8: Tamil Nadu
A9: C008 | B9: Suresh | C9: Coimbatore | D9: Tamil Nadu
A10: C009 | B10: Asha | C10: Mysore | D10: Karnataka
A11: C010 | B11: John | C11: Kochi | D11: Kerala

Sheet Products
A1: Product ID | B1: Product | C1: Category | D1: Cost Price | E1: Selling Price
A2: P001 | B2: Laptop | C2: Electronics | D2: 45000 | E2: 52000
A3: P002 | B3: Mobile | C3: Electronics | D3: 15000 | E3: 18000
A4: P003 | B4: Printer | C4: Electronics | D4: 8000 | E4: 9500
A5: P004 | B5: Chair | C5: Furniture | D5: 2000 | E5: 2800
A6: P005 | B6: Table | C6: Furniture | D6: 4000 | E6: 5200
A7: P006 | B7: Pen | C7: Stationery | D7: 10 | E7: 15
A8: P007 | B8: Notebook | C8: Stationery | D8: 35 | E8: 50
A9: P008 | B9: Keyboard | C9: Electronics | D9: 700 | E9: 900
A10: P009 | B10: Mouse | C10: Electronics | D10: 350 | E10: 500
A11: P010 | B11: White Board | C11: Furniture | D11: 1800 | E11: 2500

Sheet Salesperson
A1: Salesperson ID | B1: Salesperson
A2: S001 | B2: Kumar
A3: S002 | B3: Ravi
A4: S003 | B4: Ajay
A5: S004 | B5: Deepa
A6: S005 | B6: Nisha

Sheet Orders
A1: Order ID | B1: Date | C1: Customer ID | D1: Product ID | E1: Salesperson ID | F1: Qty | G1: Customer Name | H1: City | I1: State | J1: Year | K1: Month# | L1: Product Name | M1: Category | N1: Cost Price | O1: Selling Price | P1: Salesperson | Q1: Sales | R1: Cost | S1: Profit | T1: MonthName | U1: Quarter
A2: 1001 | B2: 46023 | C2: C001 | D2: P002 | E2: S001 | F2: 2 | G2: =IFERROR(INDEX(Customers!$B$2:$B$11,MATCH(C2,Customers!$A$2:$A$11,0)),"") -> Arun | H2: =IFERROR(INDEX(Customers!$C$2:$C$11,MATCH(C2,Customers!$A$2:$A$11,0)),"") -> Chennai | I2: =IFERROR(INDEX(Customers!$D$2:$D$11,MATCH(C2,Customers!$A$2:$A$11,0)),"") -> Tamil Nadu | J2: =YEAR(B2) -> 2026 | K2: =MONTH(B2) -> 1 | L2: =IFERROR(INDEX(Products!$B$2:$B$11,MATCH(D2,Products!$A$2:$A$11,0)),"") -> Mobile | M2: =IFERROR(INDEX(Products!$C$2:$C$11,MATCH(D2,Products!$A$2:$A$11,0)),"") -> Electronics | N2: =IFERROR(INDEX(Products!$D$2:$D$11,MATCH(D2,Products!$A$2:$A$11,0)),0) -> 15000 | O2: =IFERROR(INDEX(Products!$E$2:$E$11,MATCH(D2,Products!$A$2:$A$11,0)),0) -> 18000 | P2: =IFERROR(INDEX(Salesperson!$B$2:$B$6,MATCH(E2,Salesperson!$A$2:$A$6,0)),"") -> Kumar | Q2: =F2*O2 -> 36000 | R2: =F2*N2 -> 30000 | S2: =Q2-R2 -> 6000 | T2: =TEXT(B2,"mmm") -> Jan | U2: ="Q"&ROUNDUP(MONTH(B2)/3,0) -> Q1
A3: 1002 | B3: 46023 | C3: C005 | D3: P004 | E3: S002 | F3: 1 | G3: =IFERROR(INDEX(Customers!$B$2:$B$11,MATCH(C3,Customers!$A$2:$A$11,0)),"") -> Kiran | H3: =IFERROR(INDEX(Customers!$C$2:$C$11,MATCH(C3,Customers!$A$2:$A$11,0)),"") -> Kochi | I3: =IFERROR(INDEX(Customers!$D$2:$D$11,MATCH(C3,Customers!$A$2:$A$11,0)),"") -> Kerala | J3: =YEAR(B3) -> 2026 | K3: =MONTH(B3) -> 1 | L3: =IFERROR(INDEX(Products!$B$2:$B$11,MATCH(D3,Products!$A$2:$A$11,0)),"") -> Chair | M3: =IFERROR(INDEX(Products!$C$2:$C$11,MATCH(D3,Products!$A$2:$A$11,0)),"") -> Furniture | N3: =IFERROR(INDEX(Products!$D$2:$D$11,MATCH(D3,Products!$A$2:$A$11,0)),0) -> 2000 | O3: =IFERROR(INDEX(Products!$E$2:$E$11,MATCH(D3,Products!$A$2:$A$11,0)),0) -> 2800 | P3: =IFERROR(INDEX(Salesperson!$B$2:$B$6,MATCH(E3,Salesperson!$A$2:$A$6,0)),"") -> Ravi | Q3: =F3*O3 -> 2800 | R3: =F3*N3 -> 2000 | S3: =Q3-R3 -> 800 | T3: =TEXT(B3,"mmm") -> Jan | U3: ="Q"&ROUNDUP(MONTH(B3)/3,0) -> Q1
A4: 1003 | B4: 46024 | C4: C003 | D4: P001 | E4: S003 | F4: 1 | G4: =IFERROR(INDEX(Customers!$B$2:$B$11,MATCH(C4,Customers!$A$2:$A$11,0)),"") -> Rahul | H4: =IFERROR(INDEX(Customers!$C$2:$C$11,MATCH(C4,Customers!$A$2:$A$11,0)),"") -> Hyderabad | I4: =IFERROR(INDEX(Customers!$D$2:$D$11,MATCH(C4,Customers!$A$2:$A$11,0)),"") -> Telangana | J4: =YEAR(B4) -> 2026 | K4: =MONTH(B4) -> 1 | L4: =IFERROR(INDEX(Products!$B$2:$B$11,MATCH(D4,Products!$A$2:$A$11,0)),"") -> Laptop | M4: =IFERROR(INDEX(Products!$C$2:$C$11,MATCH(D4,Products!$A$2:$A$11,0)),"") -> Electronics | N4: =IFERROR(INDEX(Products!$D$2:$D$11,MATCH(D4,Products!$A$2:$A$11,0)),0) -> 45000 | O4: =IFERROR(INDEX(Products!$E$2:$E$11,MATCH(D4,Products!$A$2:$A$11,0)),0) -> 52000 | P4: =IFERROR(INDEX(Salesperson!$B$2:$B$6,MATCH(E4,Salesperson!$A$2:$A$6,0)),"") -> Ajay | Q4: =F4*O4 -> 52000 | R4: =F4*N4 -> 45000 | S4: =Q4-R4 -> 7000 | T4: =TEXT(B4,"mmm") -> Jan | U4: ="Q"&ROUNDUP(MONTH(B4)/3,0) -> Q1
A5: 1004 | B5: 46024 | C5: C004 | D5: P006 | E5: S005 | F5: 20 | G5: =IFERROR(INDEX(Customers!$B$2:$B$11,MATCH(C5,Customers!$A$2:$A$11,0)),"") -> Divya | H5: =IFERROR(INDEX(Customers!$C$2:$C$11,MATCH(C5,Customers!$A$2:$A$11,0)),"") -> Chennai | I5: =IFERROR(INDEX(Customers!$D$2:$D$11,MATCH(C5,Customers!$A$2:$A$11,0)),"") -> Tamil Nadu | J5: =YEAR(B5) -> 2026 | K5: =MONTH(B5) -> 1 | L5: =IFERROR(INDEX(Products!$B$2:$B$11,MATCH(D5,Products!$A$2:$A$11,0)),"") -> Pen | M5: =IFERROR(INDEX(Products!$C$2:$C$11,MATCH(D5,Products!$A$2:$A$11,0)),"") -> Stationery | N5: =IFERROR(INDEX(Products!$D$2:$D$11,MATCH(D5,Products!$A$2:$A$11,0)),0) -> 10 | O5: =IFERROR(INDEX(Products!$E$2:$E$11,MATCH(D5,Products!$A$2:$A$11,0)),0) -> 15 | P5: =IFERROR(INDEX(Salesperson!$B$2:$B$6,MATCH(E5,Salesperson!$A$2:$A$6,0)),"") -> Nisha | Q5: =F5*O5 -> 300 | R5: =F5*N5 -> 200 | S5: =Q5-R5 -> 100 | T5: =TEXT(B5,"mmm") -> Jan | U5: ="Q"&ROUNDUP(MONTH(B5)/3,0) -> Q1
A6: 1005 | B6: 46025 | C6: C007 | D6: P008 | E6: S004 | F6: 3 | G6: =IFERROR(INDEX(Customers!$B$2:$B$11,MATCH(C6,Customers!$A$2:$A$11,0)),"") -> Vignesh | H6: =IFERROR(INDEX(Customers!$C$2:$C$11,MATCH(C6,Customers!$A$2:$A$11,0)),"") -> Madurai | I6: =IFERROR(INDEX(Customers!$D$2:$D$11,MATCH(C6,Customers!$A$2:$A$11,0)),"") -> Tamil Nadu | J6: =YEAR(B6) -> 2026 | K6: =MONTH(B6) -> 1 | L6: =IFERROR(INDEX(Products!$B$2:$B$11,MATCH(D6,Products!$A$2:$A$11,0)),"") -> Keyboard | M6: =IFERROR(INDEX(Products!$C$2:$C$11,MATCH(D6,Products!$A$2:$A$11,0)),"") -> Electronics | N6: =IFERROR(INDEX(Products!$D$2:$D$11,MATCH(D6,Products!$A$2:$A$11,0)),0) -> 700 | O6: =IFERROR(INDEX(Products!$E$2:$E$11,MATCH(D6,Products!$A$2:$A$11,0)),0) -> 900 | P6: =IFERROR(INDEX(Salesperson!$B$2:$B$6,MATCH(E6,Salesperson!$A$2:$A$6,0)),"") -> Deepa | Q6: =F6*O6 -> 2700 | R6: =F6*N6 -> 2100 | S6: =Q6-R6 -> 600 | T6: =TEXT(B6,"mmm") -> Jan | U6: ="Q"&ROUNDUP(MONTH(B6)/3,0) -> Q1

Sheet Pivot
A1: Retail Sales Analysis – Summary Tables
A3: Monthly Sales | D3: Category Sales | G3: State Sales | J3: Salesperson Sales | M3: Top 10 Products | P3: Profit by Category
A4: Row Labels | B4: Sum of Sales | D4: Row Labels | E4: Sum of Sales | G4: Row Labels | H4: Sum of Sales | J4: Row Labels | K4: Sum of Sales | M4: Row Labels | N4: Sum of Sales | P4: Row Labels | Q4: Sum of Profit
A5: Jan | B5: 2800 | D5: Furniture | E5: 2800 | G5: Kerala | H5: 2800 | J5: Ravi | K5: 2800 | M5: Chair | N5: 2800 | P5: Furniture | Q5: 800
A6: Grand Total | B6: 2800 | D6: Grand Total | E6: 2800 | G6: Grand Total | H6: 2800 | J6: Grand Total | K6: 2800 | M6: Grand Total | N6: 2800 | P6: Grand Total | Q6: 800

Sheet Dashboard
A1: Retail Sales Dashboard
A4: Total Sales | E4: Total Profit | I4: Total Orders | M4: Average Order Value
A5: =SUM(Orders!Q2:Q6) -> 93800 | E5: =SUM(Orders!S2:S6) -> 14500 | I5: =COUNTA(Orders!A2:A6) -> 5 | M5: =AVERAGE(Orders!Q2:Q6) -> 18760
A7: Maximum Sale | E7: Minimum Sale | I7: Best Selling Product | M7: Best Salesperson
A8: =MAX(Orders!Q2:Q6) -> 52000 | E8: =MIN(Orders!Q2:Q6) -> 300 | I8: =INDEX(Pivot!M4:M9,MATCH(MAX(Pivot!N4:N9),Pivot!N4:N9,0)) -> Chair | M8: =INDEX(Pivot!J4:J9,MATCH(MAX(Pivot!K4:K9),Pivot!K4:K9,0)) -> Ravi
